biomaj_daemon/__init__.py
biomaj_daemon/daemon/__init__.py
biomaj_daemon/daemon/biomaj_daemon_web.py
biomaj_daemon/daemon/daemon_service.py
biomaj_daemon/daemon/utils.py
biomaj_daemon/daemon/wsgi.py
biomaj_daemon-3.0.24.data/scripts/biomaj_daemon_consumer.py
biomaj_daemon-3.0.24.dist-info/METADATA
biomaj_daemon-3.0.24.dist-info/WHEEL
biomaj_daemon-3.0.24.dist-info/top_level.txt
biomaj_daemon-3.0.24.dist-info/RECORD
