Metadata-Version: 2.1
Name: biomaj-daemon
Version: 3.0.24
Summary: BioMAJ daemon service
Home-page: http://biomaj.genouest.org
Author: Olivier Sallou
Author-email: olivier.sallou@irisa.fr
License: UNKNOWN
Download-URL: http://biomaj.genouest.org
Platform: UNKNOWN
Classifier: Development Status :: 5 - Production/Stable
Classifier: Environment :: Console
Classifier: Natural Language :: English
Classifier: Operating System :: POSIX :: Linux
Classifier: Intended Audience :: Science/Research
Classifier: Topic :: Scientific/Engineering :: Bio-Informatics
Classifier: License :: OSI Approved :: GNU Affero General Public License v3 or later (AGPLv3+)
Classifier: Programming Language :: Python :: 3
Requires-Dist: biomaj-core
Requires-Dist: biomaj
Requires-Dist: biomaj-user
Requires-Dist: biomaj-zipkin
Requires-Dist: redis
Requires-Dist: PyYAML
Requires-Dist: flask
Requires-Dist: python-consul
Requires-Dist: prometheus-client (>=0.0.18)
Requires-Dist: requests
Requires-Dist: flask-cors
